common/__init__.py
common/check.py
common/config.py
common/dkey_merge.py
common/get_manifest_info.py
common/get_steam_path.py
common/gl_unlock.py
common/init_text.py
common/log.py
common/main_func.py
common/manifest_down.py
common/migration.py
common/st_unlock.py
common/stack_error.py
Onekey-1.2.2.dist-info/LICENSE
Onekey-1.2.2.dist-info/METADATA
Onekey-1.2.2.dist-info/WHEEL
Onekey-1.2.2.dist-info/top_level.txt
Onekey-1.2.2.dist-info/RECORD
