Metadata-Version: 2.1
Name: Onekey
Version: 1.2.2
Summary: Onekey Steam Depot Manifest Downloader.
Home-page: https://github.com/ikunshare/Onekey
Author: ikun0014
Author-email: ikun0014@qq.com
License: GNU General Public License v3
Classifier: Programming Language :: Python
Classifier: Programming Language :: Python :: 3
Classifier: Programming Language :: Python :: 3.10
Classifier: Programming Language :: Python :: Implementation :: CPython
Classifier: Natural Language :: Chinese (Simplified)
Requires-Python: >=3.10.0
License-File: LICENSE
Requires-Dist: aiohttp
Requires-Dist: aiofiles
Requires-Dist: colorlog
Requires-Dist: ujson
Requires-Dist: vdf
Requires-Dist: requests
Requires-Dist: tqdm
